ripit/__init__.py
ripit/document.py
ripit/extractors.py
ripit/filters.py
ripit/marker.py
ripit/parser.py
ripit-1.0.2.dist-info/LICENSE
ripit-1.0.2.dist-info/METADATA
ripit-1.0.2.dist-info/WHEEL
ripit-1.0.2.dist-info/top_level.txt
ripit-1.0.2.dist-info/RECORD
