Metadata-Version: 2.1
Name: ripit
Version: 1.0.2
Summary: Python port of Boilerpipe, Boilerplate Removal and Fulltext Extraction from HTML pages
Home-page: https://github.com/sourcepirate/ripit
Author: sourcepirate
Author-email: plasmashadowx@gmail.com
License: Apache 2.0
Keywords: boilerpipe,boilerpy,html text extraction,text extraction,full text extraction
Platform: UNKNOWN
Classifier: Development Status :: 4 - Beta
Classifier: Topic :: Utilities
Classifier: License :: OSI Approved :: Apache Software License
Classifier: Programming Language :: Python :: 3
Classifier: Programming Language :: Python :: 3.6
Classifier: Programming Language :: Python :: 3.7
Classifier: Programming Language :: Python :: 3.8
Classifier: Programming Language :: Python :: 3.9
Classifier: Programming Language :: Python :: 3.10
Classifier: Programming Language :: Python :: 3.11
Requires-Python: >=3.6
License-File: LICENSE
Requires-Dist: requests>=2.32.3
